aisearchlab_py_commons/__init__.py
aisearchlab_py_commons/collection_utils.py
aisearchlab_py_commons/elastic_utils.py
aisearchlab_py_commons/encoding_utils.py
aisearchlab_py_commons/logging_utils.py
aisearchlab_py_commons-0.3.22.dist-info/METADATA
aisearchlab_py_commons-0.3.22.dist-info/WHEEL
aisearchlab_py_commons-0.3.22.dist-info/top_level.txt
aisearchlab_py_commons-0.3.22.dist-info/RECORD
